{"frames": {

"02-Avatar.png":
{
	"frame": {"x":2367,"y":2198,"w":323,"h":323},
	"rotated": false,
	"trimmed": true,
	"spriteSourceSize": {"x":83,"y":1374,"w":323,"h":323},
	"sourceSize": {"w":1155,"h":1770}
},
"03-Front.png":
{
	"frame": {"x":1317,"y":2198,"w":794,"h":1048},
	"rotated": true,
	"trimmed": true,
	"spriteSourceSize": {"x":109,"y":22,"w":794,"h":1048},
	"sourceSize": {"w":1314,"h":1492}
},
"06-Back-depth.png":
{
	"frame": {"x":1,"y":1,"w":1314,"h":1492},
	"rotated": false,
	"trimmed": false,
	"spriteSourceSize": {"x":0,"y":0,"w":1314,"h":1492},
	"sourceSize": {"w":1314,"h":1492}
},
"06-Back.png":
{
	"frame": {"x":1317,"y":1316,"w":880,"h":1470},
	"rotated": true,
	"trimmed": true,
	"spriteSourceSize": {"x":109,"y":22,"w":880,"h":1470},
	"sourceSize": {"w":1314,"h":1492}
},
"08-Background-depth.png":
{
	"frame": {"x":1,"y":1495,"w":1314,"h":1492},
	"rotated": false,
	"trimmed": false,
	"spriteSourceSize": {"x":0,"y":0,"w":1314,"h":1492},
	"sourceSize": {"w":1314,"h":1492}
},
"08-Background.png":
{
	"frame": {"x":1317,"y":1,"w":1313,"h":1475},
	"rotated": true,
	"trimmed": true,
	"spriteSourceSize": {"x":1,"y":17,"w":1313,"h":1475},
	"sourceSize": {"w":1314,"h":1492}
}},
"meta": {
	"app": "https://www.codeandweb.com/texturepacker",
	"version": "1.0",
	"image": "18-Aladdin-3072x.png",
	"format": "RGBA8888",
	"size": {"w":3072,"h":3072},
	"scale": "1.47",
	"smartupdate": "$TexturePacker:SmartUpdate:06ef8a456c595056369a64d658032fad:5179b5a9b12158c32069bf1eae087b29:d6a87d1e01ff03dee3cd73ffed7bbebc$"
}
}
